potatoscript/potatoPostgreSQL.py
potatoscript/test.py
python/potatoPostgreSQL.py
python/pyPostgreSQL.py
python/pysonPostgreSQL.py
python/xPostgreSQL.py
pysonPostgreSQL-1.0.1.dist-info/METADATA
pysonPostgreSQL-1.0.1.dist-info/WHEEL
pysonPostgreSQL-1.0.1.dist-info/top_level.txt
pysonPostgreSQL-1.0.1.dist-info/RECORD
